{
  "league_key": "Mx3",
  "league_info": {
    "league_code": "Mx3",
    "country": "Mexico",
    "league": "Liga Premier Serie B",
    "league_url_path": "",
    "country_code": "mx",
    "match_count": 155,
    "teams": {
      "CD Zap": {
        "home_matches": 4,
        "away_matches": 2
      },
      "Ciervos": {
        "home_matches": 2,
        "away_matches": 4
      },
      "Mexicali FC": {
        "home_matches": 4,
        "away_matches": 0
      },
      "Celaya FC": {
        "home_matches": 2,
        "away_matches": 2
      },
      "Cordobes": {
        "home_matches": 2,
        "away_matches": 1
      },
      "Correcaminos UAT II": {
        "home_matches": 0,
        "away_matches": 4
      },
      "Deportiva Venados": {
        "home_matches": 2,
        "away_matches": 2
      },
      "Racing Porto Palmeiras": {
        "home_matches": 2,
        "away_matches": 2
      },
      "Artesanos Metepec": {
        "home_matches": 4,
        "away_matches": 2
      },
      "CDM": {
        "home_matches": 4,
        "away_matches": 2
      },
      "Tigres de Alica": {
        "home_matches": 2,
        "away_matches": 1
      },
      "La Piedad": {
        "home_matches": 2,
        "away_matches": 2
      },
      "Lobos ULMX": {
        "home_matches": 4,
        "away_matches": 2
      },
      "Sporting Canamy": {
        "home_matches": 2,
        "away_matches": 4
      },
      "Chiapas FC": {
        "home_matches": 2,
        "away_matches": 0
      },
      "Montaneses": {
        "home_matches": 0,
        "away_matches": 4
      },
      "Los Cabos United": {
        "home_matches": 4,
        "away_matches": 2
      },
      "Colima FC": {
        "home_matches": 4,
        "away_matches": 2
      },
      "Atletico Cocula": {
        "home_matches": 2,
        "away_matches": 1
      },
      "Ensenada": {
        "home_matches": 0,
        "away_matches": 4
      },
      "Real Apodaca": {
        "home_matches": 4,
        "away_matches": 2
      },
      "Zacatepec": {
        "home_matches": 2,
        "away_matches": 4
      },
      "Toros Neza": {
        "home_matches": 2,
        "away_matches": 2
      },
      "Chapulineros": {
        "home_matches": 2,
        "away_matches": 4
      },
      "Deportivo Ayense": {
        "home_matches": 4,
        "away_matches": 2
      },
      "Aguacateros CDU": {
        "home_matches": 2,
        "away_matches": 4
      },
      "Gorilas de Juanacatlan": {
        "home_matches": 0,
        "away_matches": 2
      },
      "Poza Rica": {
        "home_matches": 2,
        "away_matches": 2
      },
      "FC Santiago": {
        "home_matches": 2,
        "away_matches": 2
      },
      "Cimarrones Sonora": {
        "home_matches": 2,
        "away_matches": 2
      },
      "Alacranes Durango": {
        "home_matches": 2,
        "away_matches": 2
      },
      "Inter Playa del Carmen": {
        "home_matches": 2,
        "away_matches": 2
      },
      "Canoneros Marina": {
        "home_matches": 1,
        "away_matches": 1
      },
      "Leones Negros II": {
        "home_matches": 0,
        "away_matches": 2
      },
      "UA Zacatecas": {
        "home_matches": 2,
        "away_matches": 2
      },
      "Mineros de Fresnillo": {
        "home_matches": 0,
        "away_matches": 4
      },
      "Gavilanes FC Matamoros": {
        "home_matches": 2,
        "away_matches": 0
      },
      "Chilpancingo": {
        "home_matches": 0,
        "away_matches": 4
      },
      "Cafetaleros Tapachula": {
        "home_matches": 2,
        "away_matches": 2
      },
      "Acatlan": {
        "home_matches": 1,
        "away_matches": 1
      },
      "Tritones Vallarta": {
        "home_matches": 2,
        "away_matches": 2
      },
      "Dragones de Oaxaca": {
        "home_matches": 2,
        "away_matches": 2
      },
      "Caja Oblatos CFD": {
        "home_matches": 0,
        "away_matches": 2
      },
      "Hidalgo": {
        "home_matches": 2,
        "away_matches": 0
      },
      "UAG Tecos": {
        "home_matches": 2,
        "away_matches": 0
      },
      "Zitacuaro": {
        "home_matches": 2,
        "away_matches": 0
      },
      "Racing II": {
        "home_matches": 2,
        "away_matches": 0
      },
      "Cordob\u00e9s": {
        "home_matches": 2,
        "away_matches": 1
      },
      "Tigres de \u00c1lica": {
        "home_matches": 2,
        "away_matches": 1
      },
      "Atl\u00e9tico Cocula": {
        "home_matches": 2,
        "away_matches": 1
      },
      "Gorilas de Juanacatl\u00e1n": {
        "home_matches": 0,
        "away_matches": 2
      },
      "Ca\u00f1oneros Marina": {
        "home_matches": 1,
        "away_matches": 1
      },
      "Acatl\u00e1n": {
        "home_matches": 1,
        "away_matches": 1
      }
    }
  },
  "example_count": 102,
  "trained_at": "2026-02-12T19:22:07.431994"
}