{
  "league_key": "Co1",
  "league_info": {
    "league_code": "Co1",
    "country": "Colombia",
    "league": "Primera A",
    "league_url_path": "",
    "country_code": "co",
    "match_count": 85,
    "teams": {
      "Llaneros FC COL": {
        "home_matches": 3,
        "away_matches": 3
      },
      "Atletico Bucaramanga": {
        "home_matches": 1,
        "away_matches": 3
      },
      "Deportivo Cali": {
        "home_matches": 4,
        "away_matches": 2
      },
      "Ind Medellin": {
        "home_matches": 3,
        "away_matches": 2
      },
      "Boyaca Chico": {
        "home_matches": 3,
        "away_matches": 3
      },
      "America de Cali": {
        "home_matches": 2,
        "away_matches": 3
      },
      "Rionegro Aguilas": {
        "home_matches": 2,
        "away_matches": 2
      },
      "Deportivo Pasto": {
        "home_matches": 3,
        "away_matches": 3
      },
      "Millonarios": {
        "home_matches": 3,
        "away_matches": 2
      },
      "Junior Barranquilla": {
        "home_matches": 2,
        "away_matches": 3
      },
      "Once Caldas": {
        "home_matches": 3,
        "away_matches": 3
      },
      "Ind Santa Fe": {
        "home_matches": 1,
        "away_matches": 4
      },
      "Cucuta Deportivo": {
        "home_matches": 3,
        "away_matches": 1
      },
      "Fortaleza COL": {
        "home_matches": 3,
        "away_matches": 2
      },
      "Deportes Tolima": {
        "home_matches": 2,
        "away_matches": 3
      },
      "Alianza Petrolera": {
        "home_matches": 3,
        "away_matches": 0
      },
      "Deportivo Pereira": {
        "home_matches": 1,
        "away_matches": 3
      },
      "Jaguares de Cordoba": {
        "home_matches": 2,
        "away_matches": 2
      },
      "La Equidad": {
        "home_matches": 2,
        "away_matches": 3
      },
      "Atletico Nacional": {
        "home_matches": 2,
        "away_matches": 1
      }
    }
  },
  "example_count": 48,
  "result_accuracy": 0.2,
  "ou_accuracy": 0.3,
  "trained_at": "2026-02-20T09:06:17.468281"
}