{
  "league_key": "La1",
  "league_info": {
    "league_code": "La1",
    "country": "Laos",
    "league": "Lao League",
    "league_url_path": "",
    "country_code": "la",
    "match_count": 19,
    "teams": {
      "Namtha United": {
        "home_matches": 2,
        "away_matches": 1
      },
      "Salavan United": {
        "home_matches": 0,
        "away_matches": 2
      },
      "Viengchanh": {
        "home_matches": 2,
        "away_matches": 1
      },
      "Savannakhet": {
        "home_matches": 1,
        "away_matches": 1
      },
      "Luangprabang United": {
        "home_matches": 2,
        "away_matches": 0
      },
      "Master 7 FC": {
        "home_matches": 0,
        "away_matches": 1
      },
      "Lao Army": {
        "home_matches": 1,
        "away_matches": 3
      },
      "Ezra": {
        "home_matches": 1,
        "away_matches": 0
      },
      "Young Elephant": {
        "home_matches": 1,
        "away_matches": 1
      }
    }
  },
  "example_count": 10,
  "result_accuracy": 1.0,
  "ou_accuracy": 0.5,
  "trained_at": "2026-02-19T09:52:48.745676"
}